icinga2apic/__init__.py
icinga2apic/actions.py
icinga2apic/base.py
icinga2apic/client.py
icinga2apic/configfile.py
icinga2apic/events.py
icinga2apic/exceptions.py
icinga2apic/objects.py
icinga2apic/status.py
icinga2apic-0.7.5.dist-info/LICENSE.txt
icinga2apic-0.7.5.dist-info/METADATA
icinga2apic-0.7.5.dist-info/WHEEL
icinga2apic-0.7.5.dist-info/top_level.txt
icinga2apic-0.7.5.dist-info/RECORD
