Metadata-Version: 2.1
Name: icinga2apic
Version: 0.7.5
Summary: Python Icinga 2 API - Continued
Home-page: https://github.com/joni1993/icinga2apic
Author: Christian Jonak-Möchel, fmnisme, Tobias von der Krone
Author-email: christian@jonak.org, fmnisme@gmail.com, tobias@vonderkrone.info
License: 2-Clause BSD
Keywords: Icinga,api
Platform: UNKNOWN
Requires-Dist: requests
